{
  "en": [
    {
      "title": "GitHub @GetToSet",
      "icon": "github",
      "link": "https://github.com/GetToSet/",
      "color": "var(--link-default)",
      "activeColor": "var(--link-white)",
      "activeBackgroundColor": "var(--link-black)"
    },
    {
      "title": "Unsplash @ethanwong",
      "icon": "unsplash",
      "link": "https://unsplash.com/@ethanwong/",
      "color": "var(--link-default)",
      "activeColor": "var(--link-white)",
      "activeBackgroundColor": "var(--link-black)"
    },
    {
      "title": "Instagram @gettoset",
      "icon": "instagram",
      "link": "https://instagram.com/gettoset/",
      "color": "var(--link-default)",
      "activeColor": "var(--link-white)",
      "activeBackgroundColor": "var(--link-black)"
    },
    {
      "title": "Notion @ethanwong",
      "icon": "notion",
      "link": "https://ethanwong.notion.site/",
      "color": "var(--link-default)",
      "activeColor": "var(--link-white)",
      "activeBackgroundColor": "var(--link-black)",
      "zhBadge": true
    },
    {
      "title": "Twitter @e1hanw0ng",
      "icon": "twitter",
      "link": "https://twitter.com/e1hanw0ng/",
      "color": "#1da1f2"
    },
    {
      "title": "Dribbble @GetToSet",
      "icon": "dribbble",
      "link": "https://dribbble.com/GetToSet/",
      "color": "#ea4c89"
    }
  ],
  "zh": [
    {
      "title": "GitHub @GetToSet",
      "icon": "github",
      "link": "https://github.com/GetToSet/",
      "color": "var(--link-default)",
      "activeColor": "var(--link-white)",
      "activeBackgroundColor": "var(--link-black)"
    },
    {
      "title": "Unsplash @ethanwong",
      "icon": "unsplash",
      "link": "https://unsplash.com/@ethanwong/",
      "color": "var(--link-default)",
      "activeColor": "var(--link-white)",
      "activeBackgroundColor": "var(--link-black)"
    },
    {
      "title": "Dribbble @GetToSet",
      "icon": "dribbble",
      "link": "https://dribbble.com/GetToSet/",
      "color": "#ea4c89"
    },
    {
      "title": "Notion @ethanwong",
      "icon": "notion",
      "link": "https://ethanwong.notion.site/",
      "color": "var(--link-default)",
      "activeColor": "var(--link-white)",
      "activeBackgroundColor": "var(--link-black)"
    },
    {
      "title": "Twitter @e1hanw0ng",
      "icon": "twitter",
      "link": "https://twitter.com/e1hanw0ng/",
      "color": "#1da1f2"
    },
    {
      "title": "即刻 @兔仔很忙",
      "icon": "jike",
      "link": "https://web.okjike.com/u/6AA96646-68E7-4614-843F-D0F8D271FDB6/",
      "color": "#ffe411"
    }
  ]
}